{
  "restart": {
    "file": "",
    "index": 79,
    "fixF": false,
    "F": 60
  },
  "plot": true,
  "continuation": {
    "method": "psa",
    "formula": "keller",
    "dir": 1,
    "npts": 5000,
    "tol": 0.001,
    "itermin": 1,
    "iteropt": 4,
    "itermax": 7,
    "s0": 0.001,
    "nadapt": 2,
    "smin": 1e-05,
    "smax": 0.01,
    "betacontrol": false,
    "betamax": 20,
    "fmin": 140,
    "fmax": 200,
    "NNM": 2,
    "eig_scale": 0.0001
  },
  "shooting": {
    "npts": 100,
    "npts_fail": 100,
    "nperiod": 3,
    "rel_tol": 1e-08
  },
  "phasecond": {
    "idx": "87-173"
  },
  "firstpoint": {
    "tol": 1e-05,
    "itermax": 30
  }
}
